ansible_vault_keyring/__init__.py
ansible_vault_keyring/ansible_vault_keyring.py
ansible_vault_keyring-0.2.0.dist-info/METADATA
ansible_vault_keyring-0.2.0.dist-info/WHEEL
ansible_vault_keyring-0.2.0.dist-info/entry_points.txt
ansible_vault_keyring-0.2.0.dist-info/licenses/LICENSE
ansible_vault_keyring-0.2.0.dist-info/RECORD
