Metadata-Version: 2.3
Name: ansible-vault-keyring
Version: 0.2.0
Summary: Allows ansible-vault to use the system keyring for storing vault passwords
Author: Justin Mayer
Author-email: David Groves <git@fibrecat.org>, Matt Martz <matt@sivel.net>
Requires-Python: >=3.12
Requires-Dist: ansible>=11.0.0
Requires-Dist: keyring>=25.5.0
Requires-Dist: typed-argparse>=0.3.1
